ptflops/__init__.py
ptflops/aten_engine.py
ptflops/aten_ops.py
ptflops/flops_counter.py
ptflops/pytorch_engine.py
ptflops/pytorch_ops.py
ptflops/utils.py
ptflops-0.7.5.dist-info/licenses/LICENSE
ptflops-0.7.5.dist-info/METADATA
ptflops-0.7.5.dist-info/WHEEL
ptflops-0.7.5.dist-info/top_level.txt
ptflops-0.7.5.dist-info/RECORD
