Metadata-Version: 2.4
Name: ptflops
Version: 0.7.5
Summary: Flops counter for neural networks in pytorch framework
Author-email: Vladislav Sovrasov <sovrasov.vlad@gmail.com>
Maintainer-email: Vladislav Sovrasov <sovrasov.vlad@gmail.com>
License: MIT License
Project-URL: Homepage, https://github.com/sovrasov/flops-counter.pytorch/
Project-URL: Documentation, https://github.com/sovrasov/flops-counter.pytorch/blob/master/README.md
Project-URL: Repository, https://github.com/sovrasov/flops-counter.pytorch.git
Project-URL: Bug Tracker, https://github.com/sovrasov/flops-counter.pytorch/issues
Project-URL: Changelog, https://github.com/sovrasov/flops-counter.pytorch/blob/master/CHANGELOG.md
Keywords: pytorch,cnn,transformer
Classifier: License :: OSI Approved :: MIT License
Classifier: Programming Language :: Python :: 3.9
Requires-Python: >=3.9
License-File: LICENSE
Requires-Dist: torch>=2.0
Provides-Extra: dev
Requires-Dist: flake8==5.0.1; extra == "dev"
Requires-Dist: flake8-import-order==0.18.1; extra == "dev"
Requires-Dist: isort==4.3.21; extra == "dev"
Requires-Dist: torchvision>=0.5.0; extra == "dev"
Requires-Dist: pytest==7.1.2; extra == "dev"
Requires-Dist: packaging; extra == "dev"
Dynamic: license-file
